yangsgoogle/__init__.py
yangsgoogle/generator.py
yangsgoogle/core/__init__.py
yangsgoogle/core/calendar.py
yangsgoogle/core/drive.py
yangsgoogle/core/gmail.py
yangsgoogle/core/sheets.py
yangsgoogle/credentials/__init__.py
yangsgoogle/credentials/manager.py
yangsgoogle/credentials/service_map.py
yangsgoogle-0.0.2.dist-info/METADATA
yangsgoogle-0.0.2.dist-info/RECORD
yangsgoogle-0.0.2.dist-info/WHEEL
yangsgoogle-0.0.2.dist-info/entry_points.txt
yangsgoogle-0.0.2.dist-info/top_level.txt
